shellcheck_makefile.py
shellcheck_makefile-1.27.3.dist-info/METADATA
shellcheck_makefile-1.27.3.dist-info/WHEEL
shellcheck_makefile-1.27.3.dist-info/entry_points.txt
shellcheck_makefile-1.27.3.dist-info/licenses/LICENSE
shellcheck_makefile-1.27.3.dist-info/RECORD
