Metadata-Version: 2.3
Name: shellcheck_makefile
Version: 1.27.3
Summary: Small utility for applying Shellcheck on Makefiles. Depends only on `shellcheck`, `make` and `python`.
Project-URL: repository, https://github.com/actionless/shellcheck_makefile
Author-email: Yauhen Kirylau <actionless.loveless@gmail.com>
License-File: LICENSE
Keywords: analysis,check,lint,make,makefile,shellcheck,static
Classifier: Development Status :: 5 - Production/Stable
Classifier: Environment :: Console
Classifier: Intended Audience :: Developers
Classifier: Intended Audience :: End Users/Desktop
Classifier: Intended Audience :: Information Technology
Classifier: Intended Audience :: Other Audience
Classifier: Intended Audience :: System Administrators
Classifier: License :: OSI Approved :: GNU General Public License v3 (GPLv3)
Classifier: Operating System :: POSIX :: Linux
Classifier: Programming Language :: Python :: 3.11
Classifier: Topic :: Software Development :: Build Tools
Classifier: Topic :: System :: Archiving :: Packaging
Classifier: Topic :: System :: Installation/Setup
Classifier: Topic :: Utilities
Requires-Python: >=3.12
